satif_sdk/__init__.py
satif_sdk/adapters/__init__.py
satif_sdk/adapters/code.py
satif_sdk/code_executors/__init__.py
satif_sdk/code_executors/e2b_executor.py
satif_sdk/code_executors/local_executor.py
satif_sdk/comparators/__init__.py
satif_sdk/comparators/csv.py
satif_sdk/comparators/sdif.py
satif_sdk/comparators/sdif_schema.py
satif_sdk/representers/__init__.py
satif_sdk/representers/csv.py
satif_sdk/representers/xlsx.py
satif_sdk/standardizers/__init__.py
satif_sdk/standardizers/csv.py
satif_sdk/standardizers/pdf.py
satif_sdk/standardizers/remote.py
satif_sdk/standardizers/xlsx.py
satif_sdk/transformers/__init__.py
satif_sdk/transformers/code.py
satif_sdk/transformers/matplotlib.py
satif_sdk/transformers/sql.py
satif_sdk/utils.py
satif_sdk-0.2.5.dist-info/LICENSE
satif_sdk-0.2.5.dist-info/METADATA
satif_sdk-0.2.5.dist-info/WHEEL
satif_sdk-0.2.5.dist-info/entry_points.txt
satif_sdk-0.2.5.dist-info/RECORD
