Metadata-Version: 2.3
Name: satif-sdk
Version: 0.2.5
Summary: Data SDK for AI Agents
License: MIT
Author: Syncpulse
Maintainer: Bryan Djafer
Maintainer-email: bryan.djafer@syncpulse.fr
Requires-Python: >=3.9,<4.0
Classifier: License :: OSI Approved :: MIT License
Classifier: Programming Language :: Python :: 3
Classifier: Programming Language :: Python :: 3.9
Classifier: Programming Language :: Python :: 3.10
Classifier: Programming Language :: Python :: 3.11
Classifier: Programming Language :: Python :: 3.12
Classifier: Programming Language :: Python :: 3.13
Provides-Extra: ai
Requires-Dist: aiofiles (>=24.1.0,<25.0.0)
Requires-Dist: charset-normalizer (>=3.4.1,<4.0.0)
Requires-Dist: clevercsv (>=0.8.3,<0.9.0)
Requires-Dist: deepdiff (>=8.4.2,<9.0.0)
Requires-Dist: httpx (>=0.28.1,<0.29.0)
Requires-Dist: nest-asyncio (>=1.6.0,<2.0.0)
Requires-Dist: openpyxl (>=3.1.5,<4.0.0)
Requires-Dist: pandas (>=2.0.3,<3.0.0)
Requires-Dist: python-dotenv (>=1.0.0,<2.0.0)
Requires-Dist: satif-core (>=0.2.0,<1.0.0)
Requires-Dist: sdif-db (>=0.2.0,<1.0.0)
